wechat_backup_cli/__init__.py
wechat_backup_cli/__main__.py
wechat_backup_cli/ios/__init__.py
wechat_backup_cli/ios/command/__init__.py
wechat_backup_cli/ios/command/dump_messages.py
wechat_backup_cli-0.0.1.dist-info/COPYING
wechat_backup_cli-0.0.1.dist-info/METADATA
wechat_backup_cli-0.0.1.dist-info/WHEEL
wechat_backup_cli-0.0.1.dist-info/entry_points.txt
wechat_backup_cli-0.0.1.dist-info/top_level.txt
wechat_backup_cli-0.0.1.dist-info/RECORD
